{
  "$schema": "https://ui.shadcn.com/schema/registry-item.json",
  "name": "header",
  "type": "registry:block",
  "title": "Header",
  "description": "A responsive header with navigation and mobile menu.",
  "dependencies": [
    "lucide-react"
  ],
  "registryDependencies": [
    "input",
    "avatar",
    "dropdown-menu"
  ],
  "files": [
    {
      "path": "registry/vitality/blocks/header.tsx",
      "content": "\"use client\";\n\nimport * as React from \"react\";\nimport { Search, User, Settings, LogOut, Bell } from \"lucide-react\";\n\nimport { cn } from \"@/lib/utils\";\nimport { Input } from \"@/registry/vitality/ui/input\";\nimport {\n  Avatar,\n  AvatarFallback,\n  AvatarImage,\n} from \"@/registry/vitality/ui/avatar\";\nimport {\n  DropdownMenu,\n  DropdownMenuContent,\n  DropdownMenuItem,\n  DropdownMenuLabel,\n  DropdownMenuSeparator,\n  DropdownMenuTrigger,\n} from \"@/registry/vitality/ui/dropdown-menu\";\nimport { Button } from \"../ui/button\";\n\ninterface HeaderUserMenuItem {\n  label: string;\n  href?: string;\n  onClick?: () => void;\n  icon?: React.ReactNode;\n}\n\ninterface HeaderUserProps {\n  name: string;\n  email?: string;\n  avatarSrc?: string;\n  avatarFallback?: string;\n  menuItems?: HeaderUserMenuItem[];\n}\n\ninterface HeaderProps extends React.HTMLAttributes<HTMLElement> {\n  logo?: React.ReactNode;\n  searchPlaceholder?: string;\n  onSearch?: (value: string) => void;\n  actions?: React.ReactNode;\n  user?: HeaderUserProps;\n}\n\nfunction Header({\n  className,\n  logo,\n  searchPlaceholder = \"Search...\",\n  onSearch,\n  actions,\n  user,\n  ...props\n}: HeaderProps) {\n  const defaultUserMenuItems: HeaderUserMenuItem[] = [\n    { label: \"Profile\", icon: <User className=\"h-4 w-4\" /> },\n    { label: \"Settings\", icon: <Settings className=\"h-4 w-4\" /> },\n  ];\n\n  const userMenuItems: HeaderUserMenuItem[] =\n    user?.menuItems || defaultUserMenuItems;\n\n  return (\n    <header\n      className={cn(\n        \"sticky top-0 z-50 w-full border-b bg-background/95 backdrop-blur supports-[backdrop-filter]:bg-background/60\",\n        className,\n      )}\n      {...props}\n    >\n      <div className=\"container flex items-center gap-4 p-2\">\n        {logo && <div className=\"flex items-center shrink-0\">{logo}</div>}\n        {/* Search - centered */}\n        <div className=\"relative flex-1 flex justify-center\">\n          <div className=\"relative w-full max-w-[480px]\">\n            <div className=\"bg-muted focus-visible:border-ring focus-visible:ring-ring/50 focus-visible:ring-[3px] border rounded-xl text-center gap-sm flex justify-center items-center\">\n              <Search className=\"text-muted-foreground pointer-events-none\" />\n              <Input\n                type=\"search\"\n                placeholder={searchPlaceholder}\n                className=\"border-none max-w-fit px-1 focus:max-w-[480px] focus:ring-none bg-transparent\"\n                onChange={(e) => onSearch?.(e.target.value)}\n              />\n            </div>\n          </div>\n        </div>\n\n        <div className=\"flex items-center gap-2 shrink-0\">\n          {actions}\n          {/* User info */}\n          <div className=\"flex flex-col items-end gap-0.5\">\n            <p className=\"text-sm font-semibold leading-tight\">\n              Dr Andrew Demo\n            </p>\n            <div className=\"flex items-center gap-1 text-xs text-muted-foreground\">\n              <span>Brisbane Medical Centres</span>\n              <span>·</span>\n              <span>GTU99999</span>\n            </div>\n          </div>\n\n          {/* Notifications */}\n          <Button variant=\"ghost\" size=\"sm\" className=\"rounded-full p-2\">\n            <Bell className=\"size-5 text-muted-foreground\" />\n            <span className=\"sr-only\">Notifications</span>\n          </Button>\n\n          {user && (\n            <DropdownMenu>\n              <DropdownMenuTrigger asChild>\n                <button className=\"rounded-full focus:outline-none focus:ring-2 focus:ring-ring focus:ring-offset-2\">\n                  <Avatar size=\"md\">\n                    {user.avatarSrc && (\n                      <AvatarImage src={user.avatarSrc} alt={user.name} />\n                    )}\n                    <AvatarFallback variant=\"primary\">\n                      {user.avatarFallback || user.name.charAt(0).toUpperCase()}\n                    </AvatarFallback>\n                  </Avatar>\n                </button>\n              </DropdownMenuTrigger>\n              <DropdownMenuContent align=\"end\">\n                <DropdownMenuLabel>\n                  <div className=\"flex flex-col space-y-1\">\n                    <p className=\"text-sm font-medium\">{user.name}</p>\n                    {user.email && (\n                      <p className=\"text-xs text-muted-foreground\">\n                        {user.email}\n                      </p>\n                    )}\n                  </div>\n                </DropdownMenuLabel>\n                <DropdownMenuSeparator />\n                {userMenuItems.map((item, index) => (\n                  <DropdownMenuItem\n                    key={index}\n                    onClick={item.onClick}\n                    asChild={!!item.href}\n                  >\n                    {item.href ? (\n                      <a href={item.href}>\n                        {item.icon}\n                        {item.label}\n                      </a>\n                    ) : (\n                      <>\n                        {item.icon}\n                        {item.label}\n                      </>\n                    )}\n                  </DropdownMenuItem>\n                ))}\n                <DropdownMenuSeparator />\n                <DropdownMenuItem>\n                  <LogOut className=\"h-4 w-4\" />\n                  Log out\n                </DropdownMenuItem>\n              </DropdownMenuContent>\n            </DropdownMenu>\n          )}\n        </div>\n      </div>\n    </header>\n  );\n}\n\nexport { Header, type HeaderProps, type HeaderUserProps };\n",
      "type": "registry:block"
    }
  ]
}